pyrsb.py
rsb.cpython-39-x86_64-linux-gnu.so
pyrsb.libs/librsb-4fe495e9.so.0.0.0
pyrsb.libs/libgomp-f7e03b3e.so.1.0.0
pyrsb.libs/libquadmath-2d0c479f.so.0.0.0
pyrsb.libs/libgfortran-2e0d59d6.so.5.0.0
pyrsb-0.2.20220404.2.dist-info/WHEEL
pyrsb-0.2.20220404.2.dist-info/RECORD
pyrsb-0.2.20220404.2.dist-info/LICENSE
pyrsb-0.2.20220404.2.dist-info/METADATA
pyrsb-0.2.20220404.2.dist-info/top_level.txt
