Metadata-Version: 2.1
Name: pyrsb
Version: 0.2.20220404.2
Summary: PyRSB: a Cython-based Python interface to librsb
Home-page: https://github.com/michelemartone/pyrsb
Author: Michele Martone
Author-email: michelemartone@users.sourceforge.net
License: UNKNOWN
Project-URL: Bug Tracker, https://github.com/michelemartone/pyrsb/issues
Project-URL: Source Code, https://github.com/michelemartone/pyrsb
Platform: UNKNOWN
Classifier: Programming Language :: Python :: 3
Classifier: License :: OSI Approved :: GNU General Public License v3 or later (GPLv3+)
Classifier: Operating System :: OS Independent
Requires-Python: >=3.7
License-File: LICENSE
Requires-Dist: numpy
Requires-Dist: scipy
